qcog_types/__init__.py
qcog_types/_version.py
qcog_types/intech/__init__.py
qcog_types/intech/weightedgeneral/__init__.py
qcog_types/intech/weightedgeneral/hyperparameters.py
qcog_types/pytorch_models/__init__.py
qcog_types/pytorch_models/hyperparameters.py
qcog_types/pytorch_models/tests/__init__.py
qcog_types-0.1.5.dist-info/METADATA
qcog_types-0.1.5.dist-info/WHEEL
qcog_types-0.1.5.dist-info/top_level.txt
qcog_types-0.1.5.dist-info/RECORD
