Metadata-Version: 2.4
Name: qcog_types
Version: 0.1.5
Summary: A package that exports all hyperparameter classes from different models
Author: Qognitive
Classifier: Programming Language :: Python :: 3
Requires-Python: >=3.10
Requires-Dist: pydantic>=2.0.0
Requires-Dist: requests>=2.32.4
